cocktaildb/__init__.py
cocktaildb/cocktaildb.py
cocktaildb/reqs.py
cocktaildb/requests.py
cocktail_wrapper-1.0.9.dist-info/LICENSE.md
cocktail_wrapper-1.0.9.dist-info/METADATA
cocktail_wrapper-1.0.9.dist-info/WHEEL
cocktail_wrapper-1.0.9.dist-info/top_level.txt
cocktail_wrapper-1.0.9.dist-info/RECORD
