Metadata-Version: 2.1
Name: cocktail-wrapper
Version: 1.0.9
Summary: An unofficial asynchronous API wrapper for thecocktaildb.com.
Home-page: https://github.com/clvrk/cocktail-wrapper
Author: clvrk
Author-email: herufromstatefarm@gmail.com
License: UNKNOWN
Project-URL: Funding, https://ko-fi.com/foodbot
Project-URL: Support, https://discord.gg/csUnYsr
Project-URL: Source, https://github.com/clvrk/cocktail-wrapper
Keywords: api wrapper food cocktails asynchronous library free
Platform: UNKNOWN
Classifier: License :: OSI Approved :: MIT License
Classifier: Programming Language :: Python :: 3
Classifier: Natural Language :: English
Classifier: Intended Audience :: Developers
Classifier: Operating System :: OS Independent
Requires-Python: >= 3.6
Requires-Dist: aiohttp
